{"version": "1", "message": "ERROR: Hidden Testcases server unreachable.", "problem_id": "ads2_m8_a1_1", "user_id": "bhaskaravsravya", "score": {"sample": {"0": {"execution_time": 0.3826920986175537, "passed": true}, "1": {"execution_time": 0.27233004570007324, "passed": true}, "2": {"execution_time": 1.357640266418457, "passed": true}, "3": {"execution_time": 1.0775339603424072, "passed": true}, "4": {"execution_time": 0.5514214038848877, "passed": true}, "5": {"execution_time": 2.905526876449585, "passed": true}}}, "check_style_score": "0/1"}