{"version": "1", "message": "ERROR: Hidden Testcases server unreachable.", "problem_id": "ads2_m7_a1_1", "user_id": "bhaskaravsravya", "score": {"sample": {"0": {"execution_time": 0.5599260330200195, "passed": true}, "1": {"execution_time": 0.17513132095336914, "passed": true}, "2": {"execution_time": 0.24081826210021973, "passed": true}, "3": {"execution_time": 0.19652128219604492, "passed": true}, "4": {"execution_time": 0.16439127922058105, "passed": true}, "5": {"execution_time": 0.14801549911499023, "passed": true}}}, "check_style_score": "1/1"}